edc_lab/__init__.py
edc_lab/admin_site.py
edc_lab/aliquot_types.py
edc_lab/apps.py
edc_lab/auth_objects.py
edc_lab/auths.py
edc_lab/choices.py
edc_lab/constants.py
edc_lab/list_data.py
edc_lab/managers.py
edc_lab/offline_models.py
edc_lab/patterns.py
edc_lab/post_migrate_signals.py
edc_lab/site_labs.py
edc_lab/stubs.py
edc_lab/urls.py
edc_lab/utils.py
edc_lab/wsgi.py
edc_lab/admin/__init__.py
edc_lab/admin/aliquot_admin.py
edc_lab/admin/base_model_admin.py
edc_lab/admin/box_admin.py
edc_lab/admin/box_item_admin.py
edc_lab/admin/box_type_admin.py
edc_lab/admin/consignee_admin.py
edc_lab/admin/fieldsets.py
edc_lab/admin/manifest_admin.py
edc_lab/admin/manifest_item_admin.py
edc_lab/admin/modeladmin_mixins.py
edc_lab/admin/order_admin.py
edc_lab/admin/panel_admin.py
edc_lab/admin/result_admin.py
edc_lab/admin/shipper_admin.py
edc_lab/form_validators/__init__.py
edc_lab/form_validators/crf_requisition_form_validator_mixin.py
edc_lab/form_validators/requisition_form_validator.py
edc_lab/form_validators/requisition_form_validator_mixin.py
edc_lab/forms/__init__.py
edc_lab/forms/aliquot_form.py
edc_lab/forms/box_form.py
edc_lab/forms/box_item_form.py
edc_lab/forms/box_type_form.py
edc_lab/forms/manifest_form.py
edc_lab/forms/manifest_item_form.py
edc_lab/forms/requisition_form_mixin.py
edc_lab/identifiers/__init__.py
edc_lab/identifiers/aliquot_identifier.py
edc_lab/identifiers/box_identifier.py
edc_lab/identifiers/manifest_identifier.py
edc_lab/identifiers/prefix.py
edc_lab/identifiers/requisition_identifier.py
edc_lab/lab/__init__.py
edc_lab/lab/aliquot_creator.py
edc_lab/lab/aliquot_type.py
edc_lab/lab/lab_profile.py
edc_lab/lab/manifest.py
edc_lab/lab/primary_aliquot.py
edc_lab/lab/processing_profile.py
edc_lab/lab/requisition_panel.py
edc_lab/lab/requisition_panel_group.py
edc_lab/lab/specimen.py
edc_lab/lab/specimen_processor.py
edc_lab/labels/__init__.py
edc_lab/labels/aliquot_label.py
edc_lab/labels/base_label.py
edc_lab/labels/box_label.py
edc_lab-1.0.5.dist-info/licenses/AUTHORS.rst
edc_lab-1.0.5.dist-info/licenses/LICENSE
edc_lab-1.0.5.dist-info/METADATA
edc_lab-1.0.5.dist-info/WHEEL
edc_lab-1.0.5.dist-info/top_level.txt
edc_lab-1.0.5.dist-info/RECORD
